randmat/__init__.py
randmat-0.0.1.dist-info/LICENSE
randmat-0.0.1.dist-info/METADATA
randmat-0.0.1.dist-info/WHEEL
randmat-0.0.1.dist-info/top_level.txt
randmat-0.0.1.dist-info/RECORD
